torchheat/__init__.py
torchheat/approx.py
torchheat/heat_kernel.py
torchheat/version.py
torchheat-0.2.0.dist-info/LICENSE
torchheat-0.2.0.dist-info/METADATA
torchheat-0.2.0.dist-info/WHEEL
torchheat-0.2.0.dist-info/top_level.txt
torchheat-0.2.0.dist-info/RECORD
