Metadata-Version: 2.1
Name: torchheat
Version: 0.2.0
Summary: Diffusion based distances in PyTorch
Author: Guillaume Huguet
License: MIT License
Keywords: torch,diffusion,distances,heat,kernel
Requires-Python: >=3.8
License-File: LICENSE
Requires-Dist: torch
Requires-Dist: scipy
Requires-Dist: numpy
Provides-Extra: dev
Requires-Dist: black ; extra == 'dev'
Requires-Dist: pylint ; extra == 'dev'
Requires-Dist: pytest ; extra == 'dev'
Requires-Dist: isort ; extra == 'dev'
Provides-Extra: sc
Requires-Dist: scanpy ; extra == 'sc'
